[{
	"id":"1",
	"list":"1111111111",
	"detail":{
		"aid":"11",
		"xinxi":"潘歌2019春夏新品女装大码网红仙女显瘦雪纺连衣裙印花两件套洋气时尚套装女尚11111111"
	}
},{
	"id":"2",
	"list":"2222222222",
	"detail":{
		"aid":"22",
		"xinxi":"欧美街头时尚性感挂脖露肩收腰大摆长裙连衣裙经典款欧美街头时尚性感挂脖露肩裙尚2222222222"
	}
},{
	"id":"3",
	"list":"33333333333",
	"detail":{
		"aid":"33",
		"xinxi":"北极绒 雪纺连衣裙女2019春夏季新款女装韩版时尚长袖女装A字蕾丝中沙滩长裙碎花尚33333333"
	}	
},{
	"id":"4",
	"list":"44444444444",
	"detail":{
		"aid":"44",
		"xinxi":"潘歌2019春夏新品女装大码网红仙女显瘦雪纺连衣裙印花两件套洋气时尚套装女尚4444444"
	}
},{
	"id":"5",
	"list":"5555555555555",
	"detail":{
		"aid":"55",
		"xinxi":"欧美街头时尚性感挂脖露肩收腰大摆长裙连衣裙经典款欧美街头时尚性感挂脖露肩裙尚555555"
	}	
},{
	"id":"6",
	"list":"666666666666",
	"detail":{
		"aid":"66",
		"xinxi":"北极绒 雪纺连衣裙女2019春夏季新款女装韩版时尚长袖女装A字蕾丝中长款沙滩长裙碎花666666"
	}
}]
